toxicTrig/__init__.py
toxicTrig/toxic_triggers.py
toxicTrig-0.3.0.dist-info/LICENSE
toxicTrig-0.3.0.dist-info/METADATA
toxicTrig-0.3.0.dist-info/WHEEL
toxicTrig-0.3.0.dist-info/top_level.txt
toxicTrig-0.3.0.dist-info/RECORD
