Metadata-Version: 2.1
Name: toxicTrig
Version: 0.3.0
Summary: full set of words that trigger toxicity
Home-page: https://github.com/XuhuiZhou/toxtrig
Author: Xuhui Zhou, Maarten Sap
Author-email: xuhuiz@cs.cmu.edu
Classifier: Development Status :: 3 - Alpha
Classifier: Intended Audience :: Developers
Classifier: License :: OSI Approved :: MIT License
Classifier: Programming Language :: Python :: 3
Classifier: Programming Language :: Python :: 3.7
Classifier: Programming Language :: Python :: 3.8
Requires-Python: <4,>=3.7
License-File: LICENSE
Requires-Dist: setuptools
Requires-Dist: pandas
Provides-Extra: dev
Requires-Dist: pre-commit (==3.0.1) ; extra == 'dev'
Requires-Dist: pytest (==7.1.2) ; extra == 'dev'
Requires-Dist: mypy (==1.1.1) ; extra == 'dev'
Requires-Dist: beartype (==0.12.0) ; extra == 'dev'
Requires-Dist: nbmake ; extra == 'dev'
Requires-Dist: types-setuptools ; extra == 'dev'
